vmashd/__init__.py
vmashd/audioutility.py
vmashd/config.py
vmashd/files.py
vmashd/main.py
vmashd/output.py
vmashd/videoutility.py
vmashd/tests/__init__.py
vmashd/tests/test_files.py
vmashd/tests/test_videoutility.py
vmashd-0.2.0.dist-info/LICENSE
vmashd-0.2.0.dist-info/METADATA
vmashd-0.2.0.dist-info/WHEEL
vmashd-0.2.0.dist-info/entry_points.txt
vmashd-0.2.0.dist-info/top_level.txt
vmashd-0.2.0.dist-info/RECORD
