Metadata-Version: 2.1
Name: vmashd
Version: 0.2.0
Summary: A frivolous tool to create random video/audio from provided files.
Home-page: https://pypi.org/project/vmashd/
Author: Jonathan Boone
Author-email: jeboone@gmail.com
License: MIT
Project-URL: Bug Tracker, https://github.com/boonej/vmashd/issues
Project-URL: Documentation, https://vmashd.readthedocs.io/
Project-URL: Source Code, https://github.com/boonej/vmashd
Platform: UNKNOWN
Classifier: Programming Language :: Python :: 3
Classifier: License :: OSI Approved :: MIT License
Classifier: Operating System :: OS Independent
Classifier: Topic :: Artistic Software
Classifier: Topic :: Multimedia :: Video
Requires-Python: >=3.6
License-File: LICENSE
Requires-Dist: moviepy
Requires-Dist: scikit-image
